mio/__init__.py
mio/platform.py
mio/storage.py
mio/struct.py
mio/terminal.py
mio/web.py
mio/webscrape.py
mio/work.py
rm3_mio-0.0.4.dist-info/METADATA
rm3_mio-0.0.4.dist-info/WHEEL
rm3_mio-0.0.4.dist-info/top_level.txt
rm3_mio-0.0.4.dist-info/RECORD
