Metadata-Version: 2.1
Name: rm3-mio
Version: 0.0.4
Summary: Personal Python Utilites
Home-page: https://gitlab.com/RoseMaster3000/mio
Author: Shahrose Kasim
Author-email: rosemaster3000@gmail.com
Classifier: Programming Language :: Python :: 3
Classifier: License :: OSI Approved :: MIT License
Classifier: Operating System :: OS Independent
Requires-Python: >=3.8
